GalDynPsrFreq/README.txt
GalDynPsrFreq/Shk.py
GalDynPsrFreq/__init__.py
GalDynPsrFreq/excGal.py
GalDynPsrFreq/excGalBH.py
GalDynPsrFreq/fdotdotSB1.py
GalDynPsrFreq/fdotdotSB1BH.py
GalDynPsrFreq/fdotdotSB2.py
GalDynPsrFreq/fdotdotSB2BH.py
GalDynPsrFreq/fdotdotSB3.py
GalDynPsrFreq/fdotdotSB3BH.py
GalDynPsrFreq/fdotdotSB4.py
GalDynPsrFreq/fdotdotSB4BH.py
GalDynPsrFreq/fdotdotexc.py
GalDynPsrFreq/fdotdotexcBH.py
GalDynPsrFreq/fdotdotint.py
GalDynPsrFreq/fdotexc.py
GalDynPsrFreq/fdotexcBH.py
GalDynPsrFreq/fdotint.py
GalDynPsrFreq/galpyMWBHRfo.py
GalDynPsrFreq/galpyMWBHZfo.py
GalDynPsrFreq/galpyMWRfo.py
GalDynPsrFreq/galpyMWZfo.py
GalDynPsrFreq/parameters.in
GalDynPsrFreq/read_parameters.py
GalDynPsrFreq-1.0.1.dist-info/LICENSE
GalDynPsrFreq-1.0.1.dist-info/METADATA
GalDynPsrFreq-1.0.1.dist-info/WHEEL
GalDynPsrFreq-1.0.1.dist-info/top_level.txt
GalDynPsrFreq-1.0.1.dist-info/RECORD
