Metadata-Version: 2.1
Name: GalDynPsrFreq
Version: 1.0.1
Summary: A package for estimating contribution of dynamical terms in the first and second derivatives of frequencies (both spin and orbital) of pulsars.
Home-page: https://github.com/pathakdhruv/GalDynPsrFreq
Author: Dhruv Pathak
Author-email: pathakdhruv9786@gmail.com
License: New BSD
Platform: UNKNOWN
Classifier: Programming Language :: Python :: 3
Classifier: License :: OSI Approved :: BSD License
Classifier: Operating System :: OS Independent
